doc_craft/__init__.py
doc_craft/cli.py
doc_craft/core/__init__.py
doc_craft/core/docstring_adder.py
doc_craft/core/docstring_remover.py
doc_craft/core/validate.py
doc_craft/examples/__init__.py
doc_craft/examples/python.py
doc_craft/utils/__init__.py
doc_craft/utils/apikey_handler.py
doc_craft/utils/azurekeyvault_apikey_handler.py
doc_craft/utils/env_apikey_handler.py
doc_craft/utils/llm.py
DocCraft-1.0.3.dist-info/LICENSE
DocCraft-1.0.3.dist-info/METADATA
DocCraft-1.0.3.dist-info/WHEEL
DocCraft-1.0.3.dist-info/entry_points.txt
DocCraft-1.0.3.dist-info/top_level.txt
DocCraft-1.0.3.dist-info/RECORD
