Metadata-Version: 2.1
Name: DocCraft
Version: 1.0.3
Summary: A tool to add docstrings to Python code using LLMs.
Home-page: https://github.com/nadeem4/doc_generator
Author: Nadeem Khan
Author-email: nadeem4.nk13@gmail.com
License: MIT
Classifier: Programming Language :: Python :: 3
Classifier: Operating System :: OS Independent
Classifier: Topic :: Software Development :: Code Generators
Classifier: License :: OSI Approved :: MIT License
Requires-Python: >=3.6
License-File: LICENSE
Requires-Dist: astor<0.9.0,>=0.8.1
Requires-Dist: libcst<2.0.0,>=1.4.0
Requires-Dist: openai<2.0.0,>=1.52.1
Requires-Dist: azure-identity<2.0.0,>=1.7.0
Requires-Dist: azure-keyvault-secrets<5.0.0,>=4.2.0
Requires-Dist: azure-storage-blob<13.0.0,>=12.8.0
